wxnotify/__init__.py
wxnotify/notify.py
wxnotify-0.0.1.dist-info/LICENSE
wxnotify-0.0.1.dist-info/METADATA
wxnotify-0.0.1.dist-info/WHEEL
wxnotify-0.0.1.dist-info/top_level.txt
wxnotify-0.0.1.dist-info/RECORD
