Metadata-Version: 2.1
Name: wxnotify
Version: 0.0.1
Summary: A simple wechat notification
Home-page: https://github.com/skygongque/wxnotify
Author: skygongque
Author-email: 1243650225@qq.com
License: UNKNOWN
Platform: UNKNOWN
Classifier: License :: OSI Approved :: MIT License
Classifier: Programming Language :: Python :: 3
Classifier: Intended Audience :: Developers
Classifier: Operating System :: OS Independent
Requires-Dist: requests
